Workbook

Sheet Dashboard
A1: Document Ingestion Cost Estimation Dashboard
A2: Generated: 2026-03-19
A4: QUICK COST ESTIMATOR
A5: Input Parameter | B5: Value | C5: Unit | D5: Formula Reference
A6: Documents per Month | B6: ='Input Parameters'!B6 -> 500 | C6: docs | D6: ='Input Parameters'!B5 -> Value
A7: Monthly Cost Estimate | B7: ='Cost Calculator'!B79 -> 258.54 | C7: USD | D7: ='Cost Calculator'!B30 -> Calculation
A8: Cost per Document | B8: =B6/B7 -> 1.9339367 | C8: USD | D8: =B6/B5 -> #VALUE!
A10: KEY METRICS SUMMARY
A11: Metric | B11: Current Month | C11: Previous Month | D11: Change | E11: % | F11: Status
A12: Total Monthly Cost | B12: $125.00 | C12: $118.50 | D12: $6.50 | E12: 5.5% | F12: 🟡
A13: Total Documents Processed | B13: 500 | C13: 475 | D13: 25 | E13: 5.3% | F13: 🟢
A14: Cost per Document | B14: $0.25 | C14: $0.25 | D14: $0.00 | E14: 0.0% | F14: 🟢
A15: Budget Utilization | B15: 62.5% | C15: 59.3% | D15: 3.2% | E15: 5.4% | F15: 🟢
A17: COST BREAKDOWN BY COMPONENT
A18: Component | B18: Monthly Cost | C18: % of Total | D18: Annual Projection
A19: ETL Collection | B19: $25.00 | C19: 20.0% | D19: $300.00
A20: LLM Processing (Entity Extraction) | B20: $75.00 | C20: 60.0% | D20: $900.00
A21: Embedding Generation | B21: $25.00 | C21: 20.0% | D21: $300.00
A22: Total | B22: $125.00 | C22: 100.0% | D22: $1,500.00
A24: ANNUAL PROJECTION
A25: Month | B25: Estimated Cost | C25: Actual Cost | D25: Variance | E25: Notes
A26: January | B26: $125.00 | C26: $0.00 | D26: $0.00 | E26: Forecast
A27: February | B27: $125.00 | C27: $0.00 | D27: $0.00 | E27: Forecast
A28: March | B28: $125.00 | C28: $0.00 | D28: $0.00 | E28: Forecast
A29: April | B29: $125.00 | C29: $0.00 | D29: $0.00 | E29: Forecast
A30: May | B30: $125.00 | C30: $0.00 | D30: $0.00 | E30: Forecast
A31: June | B31: $125.00 | C31: $0.00 | D31: $0.00 | E31: Forecast
A32: July | B32: $125.00 | C32: $0.00 | D32: $0.00 | E32: Forecast
A33: August | B33: $125.00 | C33: $0.00 | D33: $0.00 | E33: Forecast
A34: September | B34: $125.00 | C34: $0.00 | D34: $0.00 | E34: Forecast
A35: October | B35: $125.00 | C35: $0.00 | D35: $0.00 | E35: Forecast
A36: November | B36: $125.00 | C36: $0.00 | D36: $0.00 | E36: Forecast
A37: December | B37: $125.00 | C37: $0.00 | D37: $0.00 | E37: Forecast
A38: Annual Total | B38: $1,500.00 | C38: $0.00 | D38: $0.00
A40: BUDGET STATUS INDICATORS
A41: Metric | B41: Threshold | C41: Current | D41: Status
A42: Monthly Budget | B42: $200.00 | C42: $125.00 | D42: 🟢 Under Budget
A43: Cost per Document | B43: $0.50 | C43: $0.25 | D43: 🟢 Efficient
A44: Processing Quality | B44: 90% | C44: 95% | D44: 🟢 Excellent
A45: Cache Hit Rate | B45: 80% | C45: 85% | D45: 🟢 Optimal
A47: INSTRUCTIONS
A48: 1. Update 'Input Parameters' sheet to adjust document volumes and model selection
A49: 2. Check 'Pricing Reference' sheet to ensure API prices are current
A50: 3. Use 'Scenario Comparison' sheet to evaluate different configurations
A51: 4. Record actual costs in 'Historical Validation' sheet for accuracy tracking

Sheet Input Parameters
A1: INPUT PARAMETERS - Document Ingestion Cost Estimation
A2: Last Updated: 2026-03-19
A4: DOCUMENT CHARACTERISTICS
A5: Parameter | B5: Value | C5: Unit | D5: Notes
A6: Total Documents per Month | B6: 500 | C6: docs | D6: Combined policy + news
A7: - Policy Documents | B7: 200 | C7: docs | D7: Weekly collection
A8: - News Articles | B8: 300 | C8: docs | D8: Daily collection
A9: Average Document Length | B9: 5000 | C9: tokens | D9: Conservative estimate, adjust based on actual Avg toekns News - 2500 Avg Tokens Policy - 3750 (Some files are too big ~ 30k+ toks)
A10: Document Language Mix | B10: 100 | C10: % | D10: Multilingual (affects embedding quality)
A12: CHUNK CONFIGURATION
A13: Parameter | B13: Value | C13: Unit | D13: Notes
A14: Default Chunk Size | B14: 1500 | C14: tokens | D14: Safety margin below 128K limit
A15: Adaptive Max Chunk Size | B15: 3000 | C15: tokens | D15: For large documents
A16: Chunk Overlap Percentage | B16: 10 | C16: % | D16: Context preservation between chunks
A17: Max Chunks per Document | B17: 10 | C17: chunks | D17: With chunk limiting strategy (0 = unlimited)
A18: Average Chunks per Document | C18: chunks | D18: Formula: =CEILING(B5/B11,1)
B19: =CEILING(B9/B14,1) -> 4
A20: MODEL SELECTION
A21: Parameter | B21: Value | C21: Options | D21: Notes
A22: LLM Model for Entity Extraction | B22: gpt-4o-mini | C22: gpt-4o-mini, gpt-4o, claude-sonnet-4, claude-haiku | D22: Cost vs quality tradeoff
A23: Embedding Model | B23: text-embedding-ada-002 | C23: text-embedding-3-small, text-embedding-3-large, text-embedding-ada-002 | D23: Current production model
A24: Enable Prompt Caching | B24: YES | C24: YES, NO | D24: 90% discount (Anthropic) / 50% (OpenAI)
A25: Expected Cache Hit Rate | B25: 0.85 | C25: % | D25: With prompt caching enabled
A27: PROCESSING CONFIGURATION
A28: Parameter | B28: Value | C28: Unit | D28: Notes
A29: Batch Size | B29: 100 | C29: docs | D29: Ray Data processing batch
A30: Parallel Workers | B30: 4 | C30: workers | D30: Concurrent processing
A31: Enable Chunk Limiting | B31: YES | C31: YES, NO | D31: Reduces costs for large docs (39-85% savings)
A32: Retry/Error Overhead | B32: 15 | C32: % | D32: Buffer for failures and retries
A34: ETL COLLECTION SETTINGS
A35: Parameter | B35: Value | C35: Unit | D35: Notes
A36: Exa.ai Queries per Document | B36: 2 | C36: queries | D36: Average for policy landscape
A37: Apify Documents per Request | B37: 10 | C37: docs | D37: News aggregation batch size
A38: Max Results per Query | B38: 10 | C38: results | D38: ETL collection limit
A39: Collection Frequency (Policy) | B39: Weekly | D39: 7-day lookback
A40: Collection Frequency (News) | B40: Daily | D40: 24-hour lookback
A42: SCHEMA OVERHEAD (Auto-calculated)
A43: Parameter | B43: Value | C43: Unit | D43: Notes
A44: Entity Schema Size | B44: 5400 | C44: tokens | D44: Graphiti entity type definitions
A45: Edge Schema Size | B45: 13000 | C45: tokens | D45: Graphiti relationship type definitions
A46: Total Schema Overhead per Chunk | B46: =B44+B45 -> 18400 | C46: tokens | D46: =B37+B38 (sent with each LLM call) -> #NAME?
A47: Effective Schema Tokens (Cached) | B47: =B46*(1-B25) -> 2760 | C47: tokens
A49: QUALITY VS COST TRADEOFF
A50: Configuration | B50: Monthly Cost | C50: Quality Score | D50: Recommended For
A51: Low Cost (gpt-4o-mini + embedding-3-small) | B51: $125 | C51: Good (90%) | D51: High volume, budget-conscious
A52: Balanced (gpt-4o-mini + embedding-ada-002) | B52: $185 | C52: Excellent (100% multilingual) | D52: Production default
A53: High Quality (claude-sonnet + embedding-3-large) | B53: $425 | C53: Premium (95%+ accuracy) | D53: Critical analysis
A55: NOTES AND ASSUMPTIONS
A56: 1. Document length varies widely; 5,000 tokens is conservative average
A57: 2. Cache hit rate assumes warm cache; cold start may be lower (50-60%)
A58: 3. Schema overhead applies per chunk with entity/edge extraction
A59: 4. Chunk limiting strategy reduces chunks for large docs (>50K tokens)
A60: 5. ETL costs are estimates; actual pricing from Exa.ai/Apify may vary

Sheet Pricing Reference
A1: PRICING REFERENCE - API Costs (per 1M tokens unless noted)
A2: Last Updated: 2026-03-19
A3: Source: apisix/config/llm_pricing.yaml + External APIs
A5: ETL COLLECTION COSTS (External APIs)
A6: Service | B6: Cost Type | C6: Unit Cost | D6: Unit | E6: Notes | F6: Update Required
A7: Exa.ai | B7: Per Query | C7: $0.05 | D7: query | E7: PLACEHOLDER - Update with actual pricing | F7: YES
A8: Apify | B8: Per Document | C8: $0.01 | D8: document | E8: PLACEHOLDER - Update with actual pricing | F8: YES
A9: Web Search | B9: Per Request | C9: $0.01 | D9: search | E9: SDK cost tracker hardcoded value | F9: NO
A11: OPENAI LLM MODELS (Chat/Completion)
A12: Model | B12: Input Cost | C12: Output Cost | D12: Context Window | E12: Best For
A13: gpt-4o-mini | B13: $0.15 | C13: $0.60 | D13: 128K tokens | E13: Production entity extraction
A14: gpt-4o | B14: $2.50 | C14: $10.00 | D14: 128K tokens | E14: High accuracy requirements
A15: gpt-4-turbo | B15: $10.00 | C15: $30.00 | D15: 128K tokens | E15: Complex analysis (expensive)
A16: gpt-3.5-turbo | B16: $0.50 | C16: $1.50 | D16: 16K tokens | E16: Legacy (not recommended)
A18: ANTHROPIC LLM MODELS (Chat/Completion)
A19: Model | B19: Input Cost | C19: Output Cost | D19: Context Window | E19: Best For | F19: Cache Discount
A20: claude-3-5-sonnet-20241022 | B20: $3.00 | C20: $15.00 | D20: 200K tokens | E20: Balanced quality/cost | F20: 90%
A21: claude-3-5-haiku-20241022 | B21: $1.00 | C21: $5.00 | D21: 200K tokens | E21: Fast processing | F21: 90%
A22: claude-3-opus-20240229 | B22: $15.00 | C22: $75.00 | D22: 200K tokens | E22: Premium quality (expensive) | F22: 90%
A23: claude-3-haiku-20240307 | B23: $0.25 | C23: $1.25 | D23: 200K tokens | E23: Budget option | F23: 90%
A25: EMBEDDING MODELS (OpenAI)
A26: Model | B26: Input Cost | C26: Output Cost | D26: Dimensions | E26: Multilingual Quality | F26: Recommended
A27: text-embedding-3-small | B27: $0.02 | C27: $0.00 | D27: 1536 | E27: Poor (13%) | F27: Current production
A28: text-embedding-3-large | B28: $0.13 | C28: $0.00 | D28: 3072 | E28: Moderate (25%) | F28: High quality option
A29: text-embedding-ada-002 | B29: $0.10 | C29: $0.00 | D29: 1536 | E29: Excellent (100%) | F29: Best multilingual
A31: PROMPT CACHING DISCOUNTS
A32: Provider | B32: Cache Write Cost | C32: Cache Read Discount | D32: Minimum Cacheable | E32: Notes
A33: OpenAI | B33: Same as input | C33: 50% | D33: 1024 tokens | E33: Automatic prefix caching
A34: Anthropic | B34: 25% of input cost | C34: 90% | D34: 1024 tokens | E34: Explicit cache_control markers
A36: COST OPTIMIZATION STRATEGIES
A37: Strategy | B37: Savings Potential | C37: Implementation | D37: Status
A38: Chunk Limiting (large docs) | B38: 39-85% | C38: Enabled in config | D38: IMPLEMENTED
A39: Prompt Caching (schema) | B39: 50-90% on schema tokens | C39: Enable in LLM client | D39: IMPLEMENTED
A40: Smaller Embedding Model | B40: 80% vs ada-002 | C40: Use text-embedding-3-small | D40: IMPLEMENTED
A41: Batch Processing | B41: Indirect (throughput) | C41: Ray Data batching | D41: IMPLEMENTED
A43: CALCULATED COSTS (Helper Formulas)
A44: Description | B44: Formula | C44: Result | D44: Notes
A45: Cost per 1K tokens (gpt-4o-mini input) | B45: =B8/1000 -> #VALUE! | C45: $0.00015 | D45: For smaller calculations
A46: Cost per 1K tokens (gpt-4o-mini output) | B46: =C8/1000 -> #VALUE! | C46: $0.00060 | D46: For smaller calculations
A47: Cost per 1K tokens (embedding-3-small) | B47: =B18/1000 -> 0 | C47: $0.00002 | D47: For embedding calculations
A48: Schema cost per chunk (no cache) | B48: =18600 * $B$45 -> #VALUE! | C48: $0.00279 | D48: 18.6K tokens at gpt-4o-mini rate
A49: Schema cost per chunk (85% cache) | B49: =18600 * (1-0.85) * $B$45 -> #VALUE! | C49: $0.00042 | D49: With caching, 85% discount
A51: PRICING ASSUMPTIONS AND NOTES
A52: 1. All prices are per 1 million tokens unless otherwise noted
A53: 2. ETL costs (Exa.ai, Apify) are placeholders - UPDATE WITH ACTUAL PRICING
A54: 3. OpenAI pricing from official pricing page (as of Dec 2024)
A55: 4. Anthropic pricing from official pricing page (as of Dec 2024)
A56: 5. Prompt caching requires minimum 1024 tokens to be effective
A57: 6. Cache read discount applies only to cached portion, not entire prompt
A58: 7. Schema overhead (18,600 tokens) benefits significantly from caching
A59: 8. Embedding costs apply to full document length (no output tokens)
A61: COST COMPARISON EXAMPLE (500 docs/month)
A62: Configuration | B62: Monthly LLM Cost | C62: Monthly Embed Cost | D62: Total Monthly | E62: Annual Total
A63: Cheapest (4o-mini + small) | B63: $ 75.00 | C63: $ 25.00 | D63: $100.00 | E63: $1,200.00
A64: Recommended (4o-mini + ada-002) | B64: $ 75.00 | C64: $110.00 | D64: $185.00 | E64: $2,220.00
A65: Premium (claude-sonnet + large) | B65: $325.00 | C65: $200.00 | D65: $525.00 | E65: $6,300.00
A67: UPDATE SCHEDULE
A68: Item | B68: Frequency | C68: Last Updated | D68: Next Review
A69: OpenAI Pricing | B69: Quarterly | C69: 2026-03-19 | D69: [DATE + 3 months]
A70: Anthropic Pricing | B70: Quarterly | C70: 2026-03-19 | D70: [DATE + 3 months]
A71: Exa.ai Pricing | B71: Monthly | C71: [UPDATE REQUIRED] | D71: [AFTER UPDATE]
A72: Apify Pricing | B72: Monthly | C72: [UPDATE REQUIRED] | D72: [AFTER UPDATE]

Sheet Cost Calculator
A1: COST CALCULATOR - Detailed Breakdown
A2: Auto-calculates from Input Parameters and Pricing Reference
A4: STEP 1: ETL COLLECTION COST
A5: Component | B5: Calculation | C5: Result | D5: Formula
A6: Documents to Collect | B6: From Input Parameters | C6: 500 | D6: ='Input Parameters'!B4 -> 0
A7: Exa.ai Queries per Doc | B7: From Input Parameters | C7: 2 | D7: ='Input Parameters'!B29 -> 100
A8: Total Exa.ai Queries | B8: Docs × Queries | C8: 1000 | D8: =B5*B6 -> #VALUE!
A9: Exa.ai Cost per Query | B9: From Pricing Reference | C9: $0.05 | D9: ='Pricing Reference'!C7 -> $0.05
A10: Total Exa.ai Cost | B10: Queries × Cost per Query | C10: $50.00 | D10: =B7*B8 -> #VALUE!
A12: Apify Documents | B12: Assume 50% from Apify | C12: 250 | D12: =B5*0.5 -> #VALUE!
A13: Apify Cost per Document | B13: From Pricing Reference | C13: $0.01 | D13: ='Pricing Reference'!C8 -> $0.01
A14: Total Apify Cost | B14: Docs × Cost per Doc | C14: $2.50 | D14: =B11*B12 -> #VALUE!
A16: Total ETL Collection Cost | B16: Exa.ai + Apify | C16: $52.50 | D16: =B9+B13 -> #VALUE!
A18: STEP 2: DOCUMENT CHUNKING CALCULATION
A19: Component | B19: Calculation | C19: Result | D19: Formula
A20: Average Document Length | B20: From Input Parameters | C20: 5000 | D20: ='Input Parameters'!B5 -> Value
A21: Default Chunk Size | B21: From Input Parameters | C21: 1500 | D21: ='Input Parameters'!B11 -> 0
A22: Chunks per Document (Raw) | B22: Ceiling(Length / Chunk Size) | C22: 4
A23: Chunk Limiting Enabled? | B23: From Input Parameters | C23: YES | D23: ='Input Parameters'!B26 -> 0
A24: Max Chunks per Document | B24: From Input Parameters | C24: 20 | D24: ='Input Parameters'!B13 -> Value
A25: Effective Chunks per Document | B25: If limiting enabled, MIN(raw, max) | C25: 4
A27: Total Chunks to Process | B27: Docs × Chunks per Doc | C27: 2000 | D27: =B5*B23 -> #VALUE!
A29: STEP 3: LLM PROCESSING COST (Entity Extraction)
A30: Component | B30: Calculation | C30: Result | D30: Formula
A31: Schema Overhead per Chunk | B31: Entity + Edge schemas | C31: 18600 | D31: ='Pricing Reference'!B49 -> #VALUE!
A32: Prompt Caching Enabled? | B32: From Input Parameters | C32: YES | D32: ='Input Parameters'!B19 -> 4
A33: Cache Hit Rate | B33: From Input Parameters | C33: 85% | D33: ='Input Parameters'!B20 -> 0
A34: Effective Schema Tokens | B34: Schema × (1 - Cache Rate) | C34: 2790 | D34: =B28*(1-B30) -> #VALUE!
A36: Total Schema Input Tokens | B36: Chunks × Effective Schema | C36: 5580000 | D36: =B24*B31 -> #VALUE!
A37: Content Input Tokens (avg) | B37: Content per chunk | C37: 3000000 | D37: =B24*B19 -> #VALUE!
A38: Total Input Tokens | B38: Schema + Content | C38: 8580000 | D38: =B32+B33 -> #VALUE!
A40: Selected LLM Model | B40: From Input Parameters | C40: gpt-4o-mini | D40: ='Input Parameters'!B18 -> 0
A41: LLM Input Price (per 1M) | B41: From Pricing Reference | C41: $0.15 | D41: ='Pricing Reference'!B8 -> Per Document
A42: LLM Output Price (per 1M) | B42: From Pricing Reference | C42: $0.60 | D42: ='Pricing Reference'!C8 -> $0.01
A44: Estimated Output Tokens | B44: ~20% of input (entities) | C44: 1716000 | D44: =B34*0.2 -> #VALUE!
A46: LLM Input Cost | B46: Input Tokens × Price per M | C46: $1.29 | D46: =B34*B37/1000000 -> #VALUE!
A47: LLM Output Cost | B47: Output Tokens × Price per M | C47: $1.03 | D47: =B39*B38/1000000 -> #VALUE!
A48: Total LLM Processing Cost | B48: Input + Output | C48: $2.32 | D48: =B41+B42 -> #VALUE!
A50: STEP 4: EMBEDDING GENERATION COST
A51: Component | B51: Calculation | C51: Result | D51: Formula
A52: Total Document Length (Tokens) | B52: Docs × Avg Length | C52: 2500000 | D52: =B5*B18 -> #VALUE!
A53: Selected Embedding Model | B53: From Input Parameters | C53: text-embedding-3-small | D53: ='Input Parameters'!B19 -> 4
A54: Embedding Price (per 1M) | B54: From Pricing Reference | C54: $0.02 | D54: ='Pricing Reference'!B18 -> 0
A56: Episode Embedding Cost | B56: Length × Price per M | C56: $50.00 | D56: =B46*B48/1000000 -> #VALUE!
A58: Entity Embeddings | B58: Estimate ~200 entities/doc | C58: 100000 | D58: =B5*200 -> #VALUE!
A59: Avg Entity Name Length | B59: Tokens | C59: 10 | D59: Assumption
A60: Total Entity Tokens | B60: Entities × Avg Length | C60: 1000000 | D60: =B51*B52 -> #VALUE!
A61: Entity Embedding Cost | B61: Tokens × Price per M | C61: $20.00 | D61: =B53*B48/1000000 -> #VALUE!
A63: Relationship Embeddings | B63: Estimate ~500 edges/doc | C63: 250000 | D63: =B5*500 -> #VALUE!
A64: Avg Relationship Fact Length | B64: Tokens | C64: 20 | D64: Assumption
A65: Total Relationship Tokens | B65: Edges × Avg Length | C65: 5000000 | D65: =B56*B57 -> #VALUE!
A66: Relationship Embedding Cost | B66: Tokens × Price per M | C66: $100.00 | D66: =B58*B48/1000000 -> #VALUE!
A68: Total Embedding Cost | B68: Episode + Entity + Relationship | C68: $170.00 | D68: =B50+B54+B59 -> #VALUE!
A70: STEP 5: TOTAL COST CALCULATION
A71: Component | B71: Subtotal | C71: % of Total | D71: Notes
A72: ETL Collection Cost | B72: $52.50 | C72: 20.7% | D72: External API costs
A73: LLM Processing Cost | B73: $2.32 | C73: 0.9% | D73: Entity/relationship extraction
A74: Embedding Generation Cost | B74: $170.00 | C74: 67.1% | D74: Episodes + entities + relationships
A76: Subtotal (Before Overhead) | B76: $224.82 | C76: 88.7%
A77: Retry/Error Overhead (15%) | B77: From Input Parameters | C77: $33.72 | D77: ='Input Parameters'!B27 -> 0
A79: TOTAL MONTHLY COST | B79: 258.54 | C79: 100.0% | D79: =SUM(B64:B66)+B69 -> 0
A81: PER-DOCUMENT METRICS
A82: Metric | B82: Calculation | C82: Result | D82: Notes
A83: Cost per Document | B83: Total / Docs | C83: $0.52 | D83: =B71/B5 -> #VALUE!
A84: Cost per Chunk | B84: Total / Chunks | C84: $0.13 | D84: =B71/B24 -> #VALUE!
A85: Cost per Token (Input) | B85: LLM cost / Input tokens | C85: $0.00000027 | D85: =B43/B34 -> #VALUE!
A87: ANNUAL PROJECTION
A88: Component | B88: Monthly × 12 | C88: Annual Total
A89: Total Annual Cost | B89: Monthly cost | C89: $3,102.48 | D89: =B71*12 -> #VALUE!
A90: Total Annual Documents | B90: Monthly docs | C90: 6000 | D90: =B5*12 -> #VALUE!
A91: Annual Cost per Document | B91: Annual / Docs | C91: $0.52 | D91: =B80/B81 -> #DIV/0!
A93: COST OPTIMIZATION ANALYSIS
A94: Optimization | B94: Current | C94: Optimized | D94: Savings | E94: Notes
A95: Without Chunk Limiting | B95: $423.16 | C95: $258.54 | D95: $164.62 | E95: 39% savings with 20-chunk limit
A96: Without Prompt Caching | B96: $516.84 | C96: $258.54 | D96: $258.30 | E96: 50% savings with 85% cache hit
A97: With Premium Embedding (ada-002) | B97: $258.54 | C97: $1034.16 | D97: -$775.62 | E97: 5x more expensive, better multilingual
A99: SENSITIVITY ANALYSIS
A100: Variable | B100: Base Case | C100: +50% Change | D100: Cost Impact | E100: % Impact
A101: Document Volume | B101: 500 | C101: 750 | D101: $129.27 | E101: 50.0%
A102: Document Length | B102: 5000 | C102: 7500 | D102: $85.46 | E102: 33.1%
A103: Cache Hit Rate | B103: 85% | C103: 92.5% | D103: -$9.19 | E103: -3.6%
A104: Chunks per Doc | B104: 4 | C104: 6 | D104: $77.56 | E104: 30.0%

Sheet Scenario Comparison
A1: SCENARIO COMPARISON - What-If Analysis
A2: Compare different configurations side-by-side
A4: PRE-BUILT SCENARIOS | C4: Scenario A | D4: Scenario B | E4: Scenario C | F4: Scenario D | G4: Scenario E
A5: Scenario Name | C5: Low Volume | D5: Medium Volume | E5: High Volume | F5: Premium Quality | G5: Cost Optimized
A7: CONFIGURATION PARAMETERS
A8: Documents per Month | C8: 100 | D8: 500 | E8: 1000 | F8: 500 | G8: 500
A9: LLM Model | C9: gpt-4o-mini | D9: gpt-4o-mini | E9: gpt-4o-mini | F9: claude-sonnet-4 | G9: gpt-4o-mini
A10: Embedding Model | C10: embedding-3-small | D10: embedding-3-small | E10: embedding-3-small | F10: embedding-ada-002 | G10: embedding-3-small
A11: Prompt Caching Enabled | C11: YES | D11: YES | E11: YES | F11: YES | G11: YES
A12: Cache Hit Rate | C12: 85% | D12: 85% | E12: 85% | F12: 90% | G12: 85%
A13: Chunk Limiting Enabled | C13: YES | D13: YES | E13: YES | F13: NO | G13: YES
A14: Max Chunks per Document | C14: 20 | D14: 20 | E14: 20 | F14: Unlimited | G14: 15
A15: Average Document Length | C15: 5000 | D15: 5000 | E15: 5000 | F15: 5000 | G15: 4000
A17: COST BREAKDOWN
A18: ETL Collection Cost | C18: $10.50 | D18: $52.50 | E18: $105.00 | F18: $52.50 | G18: $52.50
A19: LLM Processing Cost | C19: $0.46 | D19: $2.32 | E19: $4.64 | F19: $82.50 | G19: $2.32
A20: Embedding Generation Cost | C20: $34.00 | D20: $170.00 | E20: $340.00 | F20: $550.00 | G20: $170.00
A21: Retry/Error Overhead (15%) | C21: $6.74 | D21: $33.72 | E21: $67.44 | F21: $102.75 | G21: $33.72
A22: Total Monthly Cost | C22: $51.71 | D22: $258.54 | E22: $517.08 | F22: $787.75 | G22: $258.54
A24: PER-DOCUMENT METRICS
A25: Cost per Document | C25: $0.52 | D25: $0.52 | E25: $0.52 | F25: $1.58 | G25: $0.52
A26: Cost per Chunk | C26: $0.17 | D26: $0.13 | E26: $0.13 | F26: $0.39 | G26: $0.15
A27: Chunks per Document | C27: 4 | D27: 4 | E27: 4 | F27: 10 | G27: 3
A29: ANNUAL PROJECTION
A30: Annual Cost | C30: $620.52 | D30: $3,102.48 | E30: $6,204.96 | F30: $9,453.00 | G30: $3,102.48
A31: Annual Documents | C31: 1200 | D31: 6000 | E31: 12000 | F31: 6000 | G31: 6000
A32: Annual Cost per Document | C32: $0.52 | D32: $0.52 | E32: $0.52 | F32: $1.58 | G32: $0.52
A34: COST COMPONENT PERCENTAGES
A35: ETL % | C35: 20% | D35: 20% | E35: 20% | F35: 7% | G35: 20%
A36: LLM Processing % | C36: 1% | D36: 1% | E36: 1% | F36: 10% | G36: 1%
A37: Embedding % | C37: 66% | D37: 66% | E37: 66% | F37: 70% | G37: 66%
A38: Overhead % | C38: 13% | D38: 13% | E38: 13% | F38: 13% | G38: 13%
A40: QUALITY INDICATORS
A41: LLM Quality Score | C41: Good (90%) | D41: Good (90%) | E41: Good (90%) | F41: Premium (95%+) | G41: Good (90%)
A42: Embedding Multilingual | C42: Poor (13%) | D42: Poor (13%) | E42: Poor (13%) | F42: Excellent (100%) | G42: Poor (13%)
A43: Processing Speed | C43: Fast | D43: Fast | E43: Fast | F43: Moderate | G43: Fast
A44: Overall Quality Rating | C44: ⭐⭐⭐ | D44: ⭐⭐⭐ | E44: ⭐⭐⭐ | F44: ⭐⭐⭐⭐⭐ | G44: ⭐⭐⭐
A46: RECOMMENDED USE CASE
A47: Best For | C47: Testing/Dev | D47: Production (budget) | E47: High-volume production | F47: Critical multilingual | G47: Aggressive cost optimization
A48: Budget Level | C48: $50-100/mo | D48: $200-300/mo | E48: $400-600/mo | F48: $700-1000/mo | G48: $200-300/mo
A49: Processing Volume | C49: <200 docs/mo | D49: 300-700 docs/mo | E49: 800-1500 docs/mo | F49: 300-700 docs/mo | G49: 300-700 docs/mo
A51: COST COMPARISON BAR CHART DATA
A52: Component | B52: Scenario A | C52: Scenario B | D52: Scenario C | E52: Scenario D | F52: Scenario E
A53: ETL | B53: $10.50 | C53: $52.50 | D53: $105.00 | E53: $52.50 | F53: $52.50
A54: LLM | B54: $0.46 | C54: $2.32 | D54: $4.64 | E54: $82.50 | F54: $2.32
A55: Embeddings | B55: $34.00 | C55: $170.00 | D55: $340.00 | E55: $550.00 | F55: $170.00
A56: Overhead | B56: $6.74 | C56: $33.72 | D56: $67.44 | E56: $102.75 | F56: $33.72
A58: CUSTOM SCENARIO BUILDER
A59: Build Your Own Scenario | D59: Value | E59: Monthly Cost | F59: Annual Cost
A60: Documents per Month | D60: 750
A61: LLM Model | D61: gpt-4o-mini (select from dropdown)
A62: Embedding Model | D62: embedding-3-small (select from dropdown)
A63: Prompt Caching | D63: YES (select YES/NO)
A64: Cache Hit Rate | D64: 85%
A65: Chunk Limiting | D65: YES (select YES/NO)
A66: Max Chunks | D66: 20 (if limiting enabled, else 0)
A67: Calculated Monthly Cost | E67: $387.81 (formula: =calculate_from_above)
A68: Calculated Annual Cost | E68: $4,653.72 (formula: =monthly*12)
A70: SCENARIO RANKING BY COST
A71: Rank | B71: Scenario | C71: Monthly Cost | D71: Annual Cost | E71: Quality Score
A72: 1 | B72: Scenario A (Low Volume) | C72: $51.71 | D72: $620.52 | E72: ⭐⭐⭐
A73: 2 | B73: Scenario B (Medium Volume) / E (Cost Optimized) | C73: $258.54 | D73: $3,102.48 | E73: ⭐⭐⭐
A74: 3 | B74: Scenario C (High Volume) | C74: $517.08 | D74: $6,204.96 | E74: ⭐⭐⭐
A75: 4 | B75: Scenario D (Premium Quality) | C75: $787.75 | D75: $9,453.00 | E75: ⭐⭐⭐⭐⭐
A77: SCENARIO RANKING BY VALUE (Cost per Quality Point)
A78: Rank | B78: Scenario | C78: Cost per Doc | D78: Quality Score | E78: Value Rating
A79: 1 | B79: Scenario B (Medium Volume) | C79: $0.52 | D79: 3.0 / 5 | E79: Best Value ✅
A80: 2 | B80: Scenario E (Cost Optimized) | C80: $0.52 | D80: 3.0 / 5 | E80: Best Value ✅
A81: 3 | B81: Scenario A (Low Volume) | C81: $0.52 | D81: 3.0 / 5 | E81: Good
A82: 4 | B82: Scenario C (High Volume) | C82: $0.52 | D82: 3.0 / 5 | E82: Good
A83: 5 | B83: Scenario D (Premium Quality) | C83: $1.58 | D83: 5.0 / 5 | E83: Premium, worth it for critical use
A85: KEY INSIGHTS
A86: 1. Embedding costs dominate (66-70% of total), even with cheapest model
A87: 2. Switching to premium embedding (ada-002) increases cost 4-5x, but provides 100% multilingual support
A88: 3. LLM processing is surprisingly cheap (1-10%) due to prompt caching effectiveness
A89: 4. Cost per document scales linearly with volume (stays constant at $0.52)
A90: 5. Premium LLM (claude-sonnet) adds significant cost but marginal quality improvement for entity extraction

Sheet Historical Validation
A1: HISTORICAL VALIDATION - Actual vs Estimated Costs
A2: Track accuracy of cost estimates over time
A4: DATA SOURCES FOR ACTUAL COSTS
A5: Source | B5: Access Method | C5: URL/Command | D5: What It Provides
A6: Cost Analytics API | B6: HTTP GET | C6: http://localhost:8090/api/costs/summary?days=30 | D6: LLM and embedding costs via APISIX
A7: TimescaleDB | B7: SQL Query | C7: SELECT sum(total_cost_usd) FROM llm_requests WHERE ... | D7: Raw cost data
A8: Grafana Dashboard | B8: Web UI | C8: http://localhost:3002/dashboards | D8: Visual cost trends
A9: SDK Cost Tracker | B9: API endpoint | C9: http://localhost:8090/api/ingest/costs | D9: Claude Agent SDK costs
A11: MONTHLY COST TRACKING
A12: Month | B12: Estimated Cost | C12: Actual Cost | D12: Variance ($) | E12: Variance (%) | F12: Actual Docs | G12: Estimated Docs | H12: Cost per Doc (Actual) | I12: Cost per Doc (Estimated) | J12: Notes
A13: January 2025 | B13: $258.54 | C13: $0.00 | D13: $0.00 | E13: 0.0% | F13: 0 | G13: 500 | H13: $0.00 | I13: $0.52 | J13: Forecast - No data yet
A14: February 2025 | B14: $258.54 | C14: $0.00 | D14: $0.00 | E14: 0.0% | F14: 0 | G14: 500 | H14: $0.00 | I14: $0.52 | J14: Forecast - No data yet
A15: March 2025 | B15: $258.54 | C15: $0.00 | D15: $0.00 | E15: 0.0% | F15: 0 | G15: 500 | H15: $0.00 | I15: $0.52 | J15: Forecast - No data yet
A16: April 2025 | B16: $258.54 | C16: $0.00 | D16: $0.00 | E16: 0.0% | F16: 0 | G16: 500 | H16: $0.00 | I16: $0.52 | J16: Forecast - No data yet
A17: May 2025 | B17: $258.54 | C17: $0.00 | D17: $0.00 | E17: 0.0% | F17: 0 | G17: 500 | H17: $0.00 | I17: $0.52 | J17: Forecast - No data yet
A18: June 2025 | B18: $258.54 | C18: $0.00 | D18: $0.00 | E18: 0.0% | F18: 0 | G18: 500 | H18: $0.00 | I18: $0.52 | J18: Forecast - No data yet
A19: July 2025 | B19: $258.54 | C19: $0.00 | D19: $0.00 | E19: 0.0% | F19: 0 | G19: 500 | H19: $0.00 | I19: $0.52 | J19: Forecast - No data yet
A20: August 2025 | B20: $258.54 | C20: $0.00 | D20: $0.00 | E20: 0.0% | F20: 0 | G20: 500 | H20: $0.00 | I20: $0.52 | J20: Forecast - No data yet
A21: September 2025 | B21: $258.54 | C21: $0.00 | D21: $0.00 | E21: 0.0% | F21: 0 | G21: 500 | H21: $0.00 | I21: $0.52 | J21: Forecast - No data yet
A22: October 2025 | B22: $258.54 | C22: $0.00 | D22: $0.00 | E22: 0.0% | F22: 0 | G22: 500 | H22: $0.00 | I22: $0.52 | J22: Forecast - No data yet
A23: November 2025 | B23: $258.54 | C23: $0.00 | D23: $0.00 | E23: 0.0% | F23: 0 | G23: 500 | H23: $0.00 | I23: $0.52 | J23: Forecast - No data yet
A24: December 2025 | B24: $258.54 | C24: $0.00 | D24: $0.00 | E24: 0.0% | F24: 0 | G24: 500 | H24: $0.00 | I24: $0.52 | J24: Forecast - No data yet
A26: SUMMARY STATISTICS | F26: Formula | G26: Result
A27: Total Estimated (YTD) | G27: $258.54
A28: Total Actual (YTD) | F28: =SUM(C13:C24) -> 0 | G28: $0.00
A29: Total Variance | F29: =C30-C29 -> 0 | G29: -$258.54
A30: Average Variance % | F30: =AVERAGE(E13:E24) -> #DIV/0! | G30: 0.0%
A31: Accuracy Rate | F31: =100% - ABS(average variance %) -> #NAME? | G31: 100.0%
A33: COST BREAKDOWN VALIDATION
A34: Component | B34: Estimated Monthly | C34: Actual Monthly | D34: Variance ($) | E34: Variance (%) | F34: Data Source
A35: ETL Collection Cost | B35: $52.50 | C35: $0.00 | D35: $0.00 | E35: 0.0% | F35: Manual tracking (Exa.ai/Apify invoices)
A36: LLM Processing Cost | B36: $2.32 | C36: $0.00 | D36: $0.00 | E36: 0.0% | F36: Cost Analytics API (agent_type filter)
A37: Embedding Generation Cost | B37: $170.00 | C37: $0.00 | D37: $0.00 | E37: 0.0% | F37: Cost Analytics API (embedding model filter)
A38: Retry/Error Overhead | B38: $33.72 | C38: $0.00 | D38: $0.00 | E38: 0.0% | F38: Calculated from error rates
A39: Total | B39: $258.54 | C39: $0.00 | D39: $0.00 | E39: 0.0% | F39: Sum of components
A41: WEEKLY TRACKING (Most Recent 12 Weeks)
A42: Week Ending | B42: Estimated Cost | C42: Actual Cost | D42: Variance ($) | E42: Variance (%) | F42: Documents Processed | G42: Cost per Doc (Actual) | H42: Notes
A43: 2026-03-19 | B43: $64.64 | C43: $0.00 | D43: $0.00 | E43: 0.0% | F43: 0 | G43: $0.00 | H43: No data yet
A44: [DATE + 7d] | B44: $64.64 | C44: $0.00 | D44: $0.00 | E44: 0.0% | F44: 0 | G44: $0.00 | H44: No data yet
A45: [DATE + 14d] | B45: $64.64 | C45: $0.00 | D45: $0.00 | E45: 0.0% | F45: 0 | G45: $0.00 | H45: No data yet
A46: [DATE + 21d] | B46: $64.64 | C46: $0.00 | D46: $0.00 | E46: 0.0% | F46: 0 | G46: $0.00 | H46: No data yet
A47: [DATE + 28d] | B47: $64.64 | C47: $0.00 | D47: $0.00 | E47: 0.0% | F47: 0 | G47: $0.00 | H47: No data yet
A48: [DATE + 35d] | B48: $64.64 | C48: $0.00 | D48: $0.00 | E48: 0.0% | F48: 0 | G48: $0.00 | H48: No data yet
A49: [DATE + 42d] | B49: $64.64 | C49: $0.00 | D49: $0.00 | E49: 0.0% | F49: 0 | G49: $0.00 | H49: No data yet
A50: [DATE + 49d] | B50: $64.64 | C50: $0.00 | D50: $0.00 | E50: 0.0% | F50: 0 | G50: $0.00 | H50: No data yet
A51: [DATE + 56d] | B51: $64.64 | C51: $0.00 | D51: $0.00 | E51: 0.0% | F51: 0 | G51: $0.00 | H51: No data yet
A52: [DATE + 63d] | B52: $64.64 | C52: $0.00 | D52: $0.00 | E52: 0.0% | F52: 0 | G52: $0.00 | H52: No data yet
A53: [DATE + 70d] | B53: $64.64 | C53: $0.00 | D53: $0.00 | E53: 0.0% | F53: 0 | G53: $0.00 | H53: No data yet
A54: [DATE + 77d] | B54: $64.64 | C54: $0.00 | D54: $0.00 | E54: 0.0% | F54: 0 | G54: $0.00 | H54: No data yet
A56: HOW TO POPULATE ACTUAL COSTS
A57: Step | B57: Command/Action | C57: Notes
A58: 1. Get LLM costs | B58: curl http://localhost:8090/api/costs/summary?days=30 | C58: Returns total_cost_usd for LLM calls
A59: 2. Get embedding costs | B59: curl http://localhost:8090/api/costs/by-model | grep 'embedding' | C59: Filter for embedding models
A60: 3. Get document count | B60: Query Neo4j: MATCH (ep:Episodic) WHERE ep.created_at > date(...) RETURN count(ep) | C60: Count episodes created in period
A61: 4. Get ETL costs | B61: Check Exa.ai and Apify invoices/dashboards | C61: Manual data entry required
A62: 5. Calculate overhead | B62: Compare total spend vs (LLM + embedding + ETL) | C62: Difference is overhead/retry costs
A63: 6. Enter actual data | B63: Update Actual Cost column in table above | C63: Use formulas to calculate variances automatically
A65: VARIANCE ANALYSIS
A66: Common Reasons for Variance | B66: Typical Impact | C66: How to Detect | D66: Mitigation
A67: Documents longer than expected | B67: +20-50% | C67: Actual docs > estimated docs for same cost | D67: Update avg doc length parameter
A68: Lower cache hit rate | B68: +50-100% | C68: LLM costs much higher than expected | D68: Check cache statistics in APISIX logs
A69: More chunks per document | B69: +30-80% | C69: Processing costs higher | D69: Review chunk limiting effectiveness
A70: Different model used | B70: +10-1000% | C70: Cost per token different | D70: Verify model selection in config
A71: ETL cost changes | B71: +/- 50% | C71: ETL costs vary | D71: Update Exa.ai/Apify pricing
A72: Processing errors/retries | B72: +10-30% | C72: Overhead > 15% | D72: Check error logs and failure rates
A74: ACCURACY IMPROVEMENT ACTIONS
A75: If Variance > 20% | B75: Action | C75: Priority
A76: Estimated too low | B76: Review input parameters; increase doc length or chunks | C76: High
A77: Estimated too high | B77: Check if chunk limiting is working as expected | C77: Medium
A78: Consistent under-estimation | B78: Increase overhead buffer from 15% to 20-25% | C78: High
A79: Consistent over-estimation | B79: Optimize caching or reduce buffer | C79: Low
A80: Variance fluctuates | B80: More granular weekly tracking needed | C80: Medium
A82: COST CONTROL ALERTS
A83: Alert Condition | B83: Threshold | C83: Current Value | D83: Status | E83: Action Required
A84: Monthly cost exceeds estimate | B84: > 120% | C84: $0.00 | D84: 🟢 OK | E84: None
A85: Cost per document too high | B85: > $0.75 | C85: $0.00 | D85: 🟢 OK | E85: None
A86: LLM costs spike | B86: > $5/month | C86: $0.00 | D86: 🟢 OK | E86: None
A87: Embedding costs spike | B87: > $250/month | C87: $0.00 | D87: 🟢 OK | E87: None
A88: Total variance | B88: > 25% | C88: 0.0% | D88: 🟢 OK | E88: None
